hv/__init__.py
hv/globals.py
hv/history_view.py
hv/interactions.py
hv/renderer.py
history_view-1.0.1.dist-info/LICENSE
history_view-1.0.1.dist-info/METADATA
history_view-1.0.1.dist-info/WHEEL
history_view-1.0.1.dist-info/entry_points.txt
history_view-1.0.1.dist-info/top_level.txt
history_view-1.0.1.dist-info/RECORD
