Metadata-Version: 2.1
Name: history-view
Version: 1.0.1
Summary: A tiny python application that abstracts viewing/interacting with your console history.
Home-page: https://github.com/semick-dev/history-view
Author: semick-dev
Author-email: sbeddall@gmail.com
License: MIT License
Project-URL: Bug Reports, https://github.com/semick-dev/history-view/issues
Project-URL: Source, https://github.com/semick-dev/history-view
Platform: UNKNOWN
Classifier: Development Status :: 4 - Beta
Classifier: Programming Language :: Python :: 3.9
Classifier: License :: OSI Approved :: MIT License
Requires-Dist: jinja2
Requires-Dist: pyperclip
